fdv_deploy/__init__.py
fdv_deploy/deploy.py
fdv_deploy-0.1.0.dist-info/METADATA
fdv_deploy-0.1.0.dist-info/WHEEL
fdv_deploy-0.1.0.dist-info/top_level.txt
fdv_deploy-0.1.0.dist-info/RECORD
